{
  "scoring_config": {
    "max_per_question": 1.5,
    "questions_per_axis": 5,
    "score_levels": [1.5, 0.5, -0.5, -1.5],
    "binary_threshold": 50,
    "median_correction": { "enabled": false, "tolerance": 5 }
  },
  "axes": [
    {
      "id": "social",
      "name": "社交軸",
      "positive_label": "社交派",
      "negative_label": "ひとり派",
      "code_positive": "E",
      "code_negative": "I",
      "display_name": "社交度",
      "invert_display": false
    },
    {
      "id": "tolerance",
      "name": "寛容軸",
      "positive_label": "寛容",
      "negative_label": "シビア",
      "code_positive": "W",
      "code_negative": "N",
      "display_name": "心の広さ度",
      "invert_display": false
    },
    {
      "id": "action",
      "name": "行動軸",
      "positive_label": "シャキシャキ",
      "negative_label": "ぐうたら",
      "code_positive": "A",
      "code_negative": "L",
      "display_name": "怠惰度",
      "invert_display": true
    },
    {
      "id": "self",
      "name": "自分大切軸",
      "positive_label": "自分優先",
      "negative_label": "他人優先",
      "code_positive": "S",
      "code_negative": "O",
      "display_name": "自分大切度",
      "invert_display": false
    }
  ],
  "sub_axes": [
    {
      "id": "logical",
      "name": "ロジカル軸",
      "positive_label": "ロジカル",
      "negative_label": "感情",
      "display_name": "ロジカル度",
      "questions_per_axis": 5,
      "max_per_question": 1.5
    }
  ],
  "axis_code_order": ["social", "tolerance", "action", "self"],
  "default_type_code": "IWLS",
  "types": [
    {
      "code": "EWAS",
      "id": "dolphin",
      "name": "盛り上げイルカ",
      "tagline": "ノリと勢いで人生を回していく",
      "description": "「とりあえずやってみよう」が口癖。場の空気は読むより作る派で、計画はなくても動ける。楽しさを最大化するためなら多少の無理は気にしないタイプ。ひとりの時間が長いとそわそわして、結局誰かに連絡しがち。",
      "tendency": "人を巻き込んで盛り上げる才能あり。ただし自分が中心にいないと急にトーン下がるし、場が冷めると一番つらいのは本人。広く浅くがちょうどいい距離感。",
      "advice": "たまには聞き役に回ると、いつもより深い話が聞けて新しい引き出しが増えるかも。",
      "axis_pattern": { "social": "+", "tolerance": "+", "action": "+", "self": "+" }
    },
    {
      "code": "EWAO",
      "id": "golden",
      "name": "太陽ゴールデン",
      "tagline": "みんなのために動くと、結果自分も嬉しい",
      "description": "場のテンションを上げるのも、下がった人を拾うのも自分の仕事だと思ってる節がある。気配り＋行動力＋明るさの三点セットで、頼られすぎてキャパオーバーになりがちなのが玉に瑕。",
      "tendency": "人間関係の調整役として誰からも好かれる。集まれば集まるほど元気になるけど、全員を助けようとして気づいたら自分のHPがゼロ、ということもしばしば。",
      "advice": "「自分も助けてもらっていい」と思っていいです。世話してる相手はあなたのことも心配してます。",
      "axis_pattern": { "social": "+", "tolerance": "+", "action": "+", "self": "-" }
    },
    {
      "code": "EWLS",
      "id": "capybara",
      "name": "マイペースカピバラ",
      "tagline": "集まりは好き、でも自分のペースは譲らない",
      "description": "人と一緒にいるのは好きだけど、テンション上げるのも気を遣うのも面倒。みんなの輪に温泉のように浸かってるのが理想。急かされるのが一番苦手。",
      "tendency": "穏やかで人当たりがいいから集まりに呼ばれやすい。けど自分から仕切ったり段取ったりはしない、できる人に任せるスタイル。",
      "advice": "「いてくれるだけで安心」と言われる人。動かないこと自体が価値、と思っていい。",
      "axis_pattern": { "social": "+", "tolerance": "+", "action": "-", "self": "+" }
    },
    {
      "code": "EWLO",
      "id": "panda",
      "name": "人気者パンダ",
      "tagline": "そこにいるだけで場が和む、けど自分は動かない",
      "description": "話しかけられやすい、頼られやすい、けど自分から動くエネルギーは少なめ。みんなが寄ってきて勝手に楽しんでくれるのが理想形。受け身だけど誰にもやさしい。",
      "tendency": "愛されキャラとして自然に立ち回るのが上手。気を遣ってる自覚は薄いけど、周りは安心して寄ってきてる。",
      "advice": "たまには自分から「これしたい」を言ってみると、周りも喜んで動いてくれます。",
      "axis_pattern": { "social": "+", "tolerance": "+", "action": "-", "self": "-" }
    },
    {
      "code": "ENAS",
      "id": "lion",
      "name": "ボスライオン",
      "tagline": "仕切るし、譲らないし、それで正解だと思ってる",
      "description": "判断早い、頭回る、空気読む、でも譲らない。リーダー気質で集団の中心にいるのが自然。「みんなのため」と言いつつ自分の意見が一番通ってる、ということがよくある。",
      "tendency": "頼れるけど怖がられがち。指示・決定が明確なので一緒に動きやすい人もいれば、息苦しく感じる人もいる二極化タイプ。",
      "advice": "「相手の意見を最初に聞く」ルールを5秒だけ守れば、慕われ度が爆上がりします。",
      "axis_pattern": { "social": "+", "tolerance": "-", "action": "+", "self": "+" }
    },
    {
      "code": "ENAO",
      "id": "bee",
      "name": "働き者ミツバチ",
      "tagline": "秩序のためなら今日も飛び続ける",
      "description": "真面目、勤勉、ルール厳守、責任感強め。集団のために動くのが当たり前。サボれない・休めない・気を抜けないの三重苦を自ら背負うタイプ。",
      "tendency": "チームに一人いると組織が回る人。ただし周りにも自分と同じ水準を求めがちで、結果として周りに息苦しさを与える可能性も。",
      "advice": "たまにはタスクを誰かに丸投げしてみてください。世界は意外と回り続けます。",
      "axis_pattern": { "social": "+", "tolerance": "-", "action": "+", "self": "-" }
    },
    {
      "code": "ENLS",
      "id": "hippo",
      "name": "どっしりカバ",
      "tagline": "言いたいことは言う、けど動くのは面倒",
      "description": "意見は明確、批評は鋭い、でも自分で動くのは気が進まない。「あれダメだよね」「あれも違うよね」と言いつつ、最後の解決策はだいたい誰かに丸投げ。",
      "tendency": "場の空気をピリッとさせる存在。仲間内では「ご意見番」扱いされるけど、本人は自分のペースを守ってるだけのつもり。",
      "advice": "批評の前に「いいね」を1つ挟むだけで、人望が3倍に変わります。",
      "axis_pattern": { "social": "+", "tolerance": "-", "action": "-", "self": "+" }
    },
    {
      "code": "ENLO",
      "id": "penguin",
      "name": "世話焼きペンギン",
      "tagline": "みんなのこと気になって結局自分が動く",
      "description": "人のことに目が行きすぎる、文句多めだけど面倒見もいい。「もう、しょうがないなあ」って言いながら、結局誰よりも先に手を出してる。お母さんっぽさが滲み出るタイプ。",
      "tendency": "周囲のケアが行き届く分、自分のことは後回し。気を遣いすぎてエネルギーが切れがち。",
      "advice": "「あの人のことは、あの人に任せる」と決めてみると、自分の時間が増えます。",
      "axis_pattern": { "social": "+", "tolerance": "-", "action": "-", "self": "-" }
    },
    {
      "code": "IWAS",
      "id": "stray_cat",
      "name": "マイペース野良ネコ",
      "tagline": "群れない、媚びない、好きに生きる",
      "description": "自分のペースで動く、他人に干渉されたくない、けど干渉も別にしない。さっぱりした関係が一番楽。「来るもの拒まず、去るもの追わず」を地で行くタイプ。",
      "tendency": "群れないけど嫌われない。独立しつつも要所では協力する、ちょうどいい距離感を保つのが上手。",
      "advice": "「気が向いた時だけ連絡する」スタイル、実は周りも心地よく受け取ってます。",
      "axis_pattern": { "social": "-", "tolerance": "+", "action": "+", "self": "+" }
    },
    {
      "code": "IWAO",
      "id": "beaver",
      "name": "黙々ビーバー",
      "tagline": "目立たないけど、いないと困るやつ",
      "description": "黙々と仕事をこなす、感謝されたい欲は薄い、けど確実に役立ってる。チームの中で「あれ、誰がやったの？」が口癖になるくらい裏方に徹するタイプ。",
      "tendency": "表に出ない貢献が多い。本人は自然に動いてるだけだけど、周りからは「縁の下の力持ち」と尊敬されてる。",
      "advice": "「私がやりました」と一回だけ言ってみると、評価が一気に追いつきます。",
      "axis_pattern": { "social": "-", "tolerance": "+", "action": "+", "self": "-" }
    },
    {
      "code": "IWLS",
      "id": "sloth",
      "name": "お人よしナマケモノ",
      "tagline": "人にはやさしく、自分には激甘",
      "description": "人にはわりとやさしいのに、自分にはとことん甘いタイプ。感情で動くせい、面倒なことは後回し。少人数やひとり時間がないと、すぐに機嫌とHPが削れます。",
      "tendency": "一見やさしく、遠慮できるされがちなタイプ。ただし心の中ではかなり省エネ運転。広く浅くより、少人数をゆるく長く付き合うほうが向いています。",
      "advice": "誘いを全部受けなくても、人間関係は案外壊れません。あなたに必要なのは、社交性よりも「行っても壊れない心配が減る」です。",
      "axis_pattern": { "social": "-", "tolerance": "+", "action": "-", "self": "+" }
    },
    {
      "code": "IWLO",
      "id": "koala",
      "name": "やさしいコアラ",
      "tagline": "ふんわり、けど誰かのために動ける",
      "description": "自分から動くのは得意じゃないけど、誰かに頼られたら案外がんばるタイプ。穏やかでマイペース、争いごとはなるべく避けたい。「ゆるく長く付き合う」が得意分野。",
      "tendency": "人にやさしい、けど距離は近づけすぎない。広く浅くより、少人数で深く長くがしっくり来る。一人時間でエネルギー回復するタイプ。",
      "advice": "頼られた時の「やります」を、たまには「今はちょっとごめん」に置き換えても誰も怒りません。",
      "axis_pattern": { "social": "-", "tolerance": "+", "action": "-", "self": "-" }
    },
    {
      "code": "INAS",
      "id": "wolf",
      "name": "一匹オオカミ",
      "tagline": "群れないし、もたれかからない",
      "description": "自分の判断で動くから決断は早く、人にも甘えない代わりに人を当てにもしない。「ひとりが快適」と言いつつ、本当は信頼できる少数の相手だけは欲しい、というのが本音。",
      "tendency": "シビアな目で世界を見てるけど、それは自分にも適用される。仕事のクオリティ高め、人付き合いの数は少なめ。誰とでも仲良くは目指してない。",
      "advice": "「弱み見せたら負け」ではなく、「弱み見せたら関係が深まる」もアリです。",
      "axis_pattern": { "social": "-", "tolerance": "-", "action": "+", "self": "+" }
    },
    {
      "code": "INAO",
      "id": "shepherd",
      "name": "忠犬シェパード",
      "tagline": "自分の仕事はちゃんとやる、それが信条",
      "description": "黙々と正確に仕事する、ミスに厳しい、人にも自分にも妥協しない。職人気質で、自分が信じた相手・チームのためなら全力を尽くす。",
      "tendency": "信頼できる相手を見極めるのに時間がかかるけど、一度信頼すれば長く続く。逆に裏切られると距離を一気に置く。",
      "advice": "たまに「完璧じゃない自分」を見せてあげると、相手も気を抜いて付き合えて関係が長持ちします。",
      "axis_pattern": { "social": "-", "tolerance": "-", "action": "+", "self": "-" }
    },
    {
      "code": "INLS",
      "id": "leopard",
      "name": "気まぐれヒョウ",
      "tagline": "他人どうでもいい、自分を大事に",
      "description": "人と関わるのが面倒、自分の世界に入りたい、けど寝てる時間が一番幸せ。気が向いた時だけ動く、それ以外はそっとしておいてほしい。",
      "tendency": "シビアな目で人を見るし、自分の領域も守る。エネルギー消費が苦手で、深い人間関係も意外と築ける、気が向けば。",
      "advice": "「気が向いた時に会えるだけで十分」と思ってくれる人を1人見つけられれば、それで満点です。",
      "axis_pattern": { "social": "-", "tolerance": "-", "action": "-", "self": "+" }
    },
    {
      "code": "INLO",
      "id": "hedgehog",
      "name": "省エネハリネズミ",
      "tagline": "気は遣う、けどなるべく動きたくない",
      "description": "周囲のことは気にしてる、ただ動くエネルギーが足りない。「やった方がいい」と思いつつ後回しにすることが多くて、罪悪感とぐうたらが綱引きしてる。",
      "tendency": "察するのは得意、行動に移すのは苦手。気を遣われる側より遣う側だけど、表に出さないから誤解されることも。",
      "advice": "思ったことを2割だけ言葉にしてみると、誤解が減って気疲れも減ります。",
      "axis_pattern": { "social": "-", "tolerance": "-", "action": "-", "self": "-" }
    }
  ]
}
